<?xml version='1.0' encoding='UTF-8' ?>
<?charles serialisation-version='2.0' ?>
<rewriteSet-array>
  <rewriteSet>
    <active>true</active>
    <name>VSCO</name>
    <hosts>
      <locationPatterns>
        <locationMatch>
          <location>
            <protocol>https</protocol>
            <host>vsco.co</host>
            <port>443</port>
            <path>/api/*</path>
          </location>
          <enabled>true</enabled>
        </locationMatch>
      </locationPatterns>
    </hosts>
    <rules>
      <rewriteRule>
        <active>true</active>
        <ruleType>7</ruleType>
        <matchValue>&quot;is_trial_period&quot;:true</matchValue>
        <matchHeaderRegex>false</matchHeaderRegex>
        <matchValueRegex>false</matchValueRegex>
        <matchRequest>false</matchRequest>
        <matchResponse>true</matchResponse>
        <newValue>&quot;is_trial_period&quot;:false</newValue>
        <newHeaderRegex>false</newHeaderRegex>
        <newValueRegex>false</newValueRegex>
        <matchWholeValue>false</matchWholeValue>
        <caseSensitive>false</caseSensitive>
        <replaceType>2</replaceType>
      </rewriteRule>
      <rewriteRule>
        <active>true</active>
        <ruleType>7</ruleType>
        <matchValue>&quot;is_active&quot;:false</matchValue>
        <matchHeaderRegex>false</matchHeaderRegex>
        <matchValueRegex>false</matchValueRegex>
        <matchRequest>false</matchRequest>
        <matchResponse>true</matchResponse>
        <newValue>&quot;is_active&quot;:true</newValue>
        <newHeaderRegex>false</newHeaderRegex>
        <newValueRegex>false</newValueRegex>
        <matchWholeValue>false</matchWholeValue>
        <caseSensitive>false</caseSensitive>
        <replaceType>2</replaceType>
      </rewriteRule>
    </rules>
  </rewriteSet>
</rewriteSet-array>